aicsshparam/__init__.py
aicsshparam/shparam.py
aicsshparam/shtools.py
docs/Makefile
docs/conf.py
docs/contributing.rst
docs/index.rst
docs/installation.rst
docs/logo.gif
docs/make.bat
docs/pc12.png
docs/table1.jpg
docs/table2.jpg
aicsshparam-0.1.11.dist-info/LICENSE
aicsshparam-0.1.11.dist-info/METADATA
aicsshparam-0.1.11.dist-info/WHEEL
aicsshparam-0.1.11.dist-info/top_level.txt
aicsshparam-0.1.11.dist-info/RECORD
