Metadata-Version: 2.2
Name: aicsshparam
Version: 0.1.11
Summary: Spherical harmonics parametrization for 3D starlike shapes
Author-email: Matheus Viana <matheus.viana@alleninstitute.org>
License: Allen Institute Software License – This software license is the 2-clause BSD
Project-URL: Homepage, https://github.com/AllenCell/aics-shparam
Keywords: aicsshparam
Classifier: Development Status :: 5 - Production/Stable
Classifier: Intended Audience :: Science/Research
Classifier: License :: Free for non-commercial use
Classifier: Natural Language :: English
Classifier: Programming Language :: Python :: 3
Requires-Python: >=3.9
License-File: LICENSE
Requires-Dist: numpy
Requires-Dist: scipy
Requires-Dist: scikit-image
Requires-Dist: scikit-learn
Requires-Dist: vtk
Requires-Dist: pyshtools
Provides-Extra: setup
Requires-Dist: pytest-runner>=5.2; extra == "setup"
Provides-Extra: test
Requires-Dist: black; extra == "test"
Requires-Dist: flake8; extra == "test"
Requires-Dist: flake8-debugger; extra == "test"
Requires-Dist: pytest; extra == "test"
Requires-Dist: pytest-cov; extra == "test"
Requires-Dist: pytest-raises; extra == "test"
Provides-Extra: dev
Requires-Dist: pytest-runner>=5.2; extra == "dev"
Requires-Dist: black; extra == "dev"
Requires-Dist: flake8; extra == "dev"
Requires-Dist: flake8-debugger; extra == "dev"
Requires-Dist: pytest; extra == "dev"
Requires-Dist: pytest-cov; extra == "dev"
Requires-Dist: pytest-raises; extra == "dev"
Requires-Dist: bump2version; extra == "dev"
Requires-Dist: coverage; extra == "dev"
Requires-Dist: ipython; extra == "dev"
Requires-Dist: myst-parser; extra == "dev"
Requires-Dist: sphinx; extra == "dev"
Requires-Dist: furo; extra == "dev"
Requires-Dist: tox; extra == "dev"
Requires-Dist: twine; extra == "dev"
Requires-Dist: wheel; extra == "dev"
Provides-Extra: all
Requires-Dist: numpy; extra == "all"
Requires-Dist: scipy; extra == "all"
Requires-Dist: scikit-image; extra == "all"
Requires-Dist: scikit-learn; extra == "all"
Requires-Dist: vtk; extra == "all"
Requires-Dist: pyshtools; extra == "all"
Requires-Dist: pytest-runner>=5.2; extra == "all"
Requires-Dist: black; extra == "all"
Requires-Dist: flake8; extra == "all"
Requires-Dist: flake8-debugger; extra == "all"
Requires-Dist: pytest; extra == "all"
Requires-Dist: pytest-cov; extra == "all"
Requires-Dist: pytest-raises; extra == "all"
Requires-Dist: bump2version; extra == "all"
Requires-Dist: coverage; extra == "all"
Requires-Dist: ipython; extra == "all"
Requires-Dist: myst-parser; extra == "all"
Requires-Dist: sphinx; extra == "all"
Requires-Dist: furo; extra == "all"
Requires-Dist: tox; extra == "all"
Requires-Dist: twine; extra == "all"
Requires-Dist: wheel; extra == "all"
